verr/__init__.py
verr-1.1.2.dist-info/LICENSE
verr-1.1.2.dist-info/METADATA
verr-1.1.2.dist-info/WHEEL
verr-1.1.2.dist-info/top_level.txt
verr-1.1.2.dist-info/RECORD
