Metadata-Version: 2.1
Name: verr
Version: 1.1.2
Summary: Represents a version number that can be parsed and compared.
Home-page: https://github.com/Amourspirit/python-version-num
Author: :Barry-Thomas-Paul: Moss
Author-email: bigbytetech@gmail.com
License: MIT
Keywords: python,version,verr
Platform: UNKNOWN
Classifier: License :: OSI Approved :: MIT License
Classifier: Programming Language :: Python :: 3
Classifier: Programming Language :: Python :: 3.6
Classifier: Programming Language :: Python :: 3.7
Classifier: Programming Language :: Python :: 3.8
Classifier: Programming Language :: Python :: 3.9
Requires-Python: >=3.6.0
License-File: LICENSE
